README.txt
setup.py
VLCmetadata01.egg-info/PKG-INFO
VLCmetadata01.egg-info/SOURCES.txt
VLCmetadata01.egg-info/dependency_links.txt
VLCmetadata01.egg-info/top_level.txt
testF/__init__.py