Metadata-Version: 1.0
Name: VLCmetadata01
Version: 0.2
Summary: UNKNOWN
Home-page: https://github.com/MartinBarker/VLC-Radio
Author: Martin Barker
Author-email: martinbarker99@gmail.com
License: Creative Commons Attribution-Noncommercial-Share Alike license
Platform: UNKNOWN
